[
  {
    "_id":1,
    "entries": [{
        "entry": {
          "type": "apprentice",
          "count": 3,
          "hoursPerPerson":24,
          "dollarsPerHour":15,
          "nightsPerPerson":2,
          "costPerNight":80
    }},
    {  
        "entry": {

          "type": "assistant",
          "count": 2,
          "hoursPerPerson":24,
          "dollarsPerHour":10,
          "nightsPerPerson":2,
          "costPerNight":80
    }}
    ],
    "subtotal": 1880
  },

  {
    "_id":2,
    "entries1": [{
        "entry": {
          "type": "apprentice",
          "count": 2,
          "hoursPerPerson":24,
          "dollarsPerHour":15,
          "nightsPerPerson":2,
          "costPerNight":80
    }},
    {  
        "entry": {
          "type": "assistant",
          "count": 1,
          "hoursPerPerson":24,
          "dollarsPerHour":10,
          "nightsPerPerson":2,
          "costPerNight":80
    }}
    ],
    "subtotal": 1200
  },

  {
    "_id":3,
    "entries1": [{
        "entry": {
          "type": "apprentice",
          "count": 2,
          "hoursPerPerson":24,
          "dollarsPerHour":15,
          "nightsPerPerson":2,
          "costPerNight":80
    }},
    {  
        "entry": {
          "type": "assistant",
          "count": 1,
          "hoursPerPerson":24,
          "dollarsPerHour":10,
          "nightsPerPerson":2,
          "costPerNight":80
    }}
    ],
    "subtotal": 1680
  }

]